<?xml version="1.0" encoding="UTF-8"?>
<!--
<!DOCTYPE doc [
<!ENTITY CONTRAST "/usr/share/icons/HighContrast/scalable">
]>
-->
<subpanel category="emacs">
<items>
  <button brief="P">
    <name>ctls</name>
    <category>panel</category>
    <icon>&CONTRAST;/actions/document-save.svg</icon>
    <command>bash -c 'xdotool key --clearmodifiers ctrl+x ctrl+s' </command>
  </button>
  <button brief="P">
    <name>mxx</name>
    <category>panel</category>
    <display>mx</display>
    <command>bash -c 'xdotool key -clearmodifiers alt+x' </command>
  </button>
  <button brief="P">
    <name>cx</name>
    <category>panel</category>
    <display>cx</display>
    <command>bash -c 'xdotool key -clearmodifiers ctrl+x' </command>
  </button>
  <button brief="P">
    <name>cg</name>
    <category>panel</category>
    <display>cg</display>
    <command>bash -c 'xdotool key -clearmodifiers ctrl+g' </command>
  </button>
  
  <button brief="P">
    <name>cxr</name>
    <category>panel</category>
    <icon>/usr/share/icons/HighContrast/scalable/actions/object-flip-horizontal.svg</icon>
    <command>bash -c 'xdotool key -clearmodifiers ctrl+x braceright' </command>
  </button>
<!-- 
  <button brief="P">
    <name>cxl</name>
    <category>panel</category>
    <display>cxl</display>
    <command>bash -c 'xdotool key -clearmodifiers ctrl+x braceleft' </command>
  </button>
 -->
  <button brief="P">
    <name>exit</name>
    <category>panel</category>
    <icon>&CONTRAST;/actions/application-exit.svg</icon>
    <command>bash -c 'xdotool key --clearmodifiers ctrl+x ctrl+c' </command>
  </button>
</items>
</subpanel>
